fm/__init__.py
fm/axial_attention.py
fm/constants.py
fm/data.py
fm/model.py
fm/modules.py
fm/multihead_attention.py
fm/pretrained.py
fm/version.py
fm/downstream/__init__.py
fm/downstream/backbones.py
fm/downstream/baseline.py
fm/downstream/downstream_module.py
fm/downstream/weights_init.py
fm/downstream/weights_load.py
fm/downstream/pairwise_predictor/__init__.py
fm/downstream/pairwise_predictor/linear_dot_product.py
fm/downstream/pairwise_predictor/pairwise_concat.py
fm/model/__init__.py
fm/model/esm1.py
rna_fm-0.2.2.data/data/source_docs/fm/LICENSE
rna_fm-0.2.2.data/data/source_docs/fm/README.md
rna_fm-0.2.2.dist-info/LICENSE
rna_fm-0.2.2.dist-info/METADATA
rna_fm-0.2.2.dist-info/WHEEL
rna_fm-0.2.2.dist-info/top_level.txt
rna_fm-0.2.2.dist-info/zip-safe
rna_fm-0.2.2.dist-info/RECORD
