Metadata-Version: 2.1
Name: rna-fm
Version: 0.2.2
Summary: RNA Foundation Model (rna-fm): Pretrained language models for RNAs. From CUHK AIH Lab.
Home-page: https://github.com/ml4bio/RNA-FM
Author: CUHK AIH Lab
License: MIT
Platform: UNKNOWN
